README.rst
setup.py
spexy/__init__.py
spexy.egg-info/PKG-INFO
spexy.egg-info/SOURCES.txt
spexy.egg-info/dependency_links.txt
spexy.egg-info/top_level.txt