Metadata-Version: 1.1
Name: spexy
Version: 0.0
Summary: Spectral Exterior Calculus
Home-page: http://github.com/drufat/spexy.git
Author: Dzhelil Rufat
Author-email: drufat@fastmail.com
License: GNU GPLv3
Platform: UNKNOWN
Requires: numpy
Requires: sympy
Requires: pybindcpp
